{
    "cmp_africansavanna_003_wildanimals_003.jpg": {
        "subject": "nnIBS Model",
        "dataset": "HSUBANOTT",
        "image_height": 24,
        "image_width": 32,
        "receptive_height": 1,
        "receptive_width": 1,
        "target_found": true,
        "target_bbox": [
            11,
            19,
            13,
            20
        ],
        "X": [
            16,
            19
        ],
        "Y": [
            12,
            11
        ],
        "elm_info_gained": [
            0.7703773611931669,
            4.033596818755272
        ],
        "searched_object_indexes": [
            0
        ],
        "memory_set": [
            "bird246.png"
        ],
        "target_object": "TBD",
        "max_fixations": 41
    },
    "cmp_building_007_person_004.jpg": {
        "subject": "nnIBS Model",
        "dataset": "HSUBANOTT",
        "image_height": 24,
        "image_width": 32,
        "receptive_height": 1,
        "receptive_width": 1,
        "target_found": false,
        "target_bbox": [
            17,
            6,
            18,
            7
        ],
        "X": [
            16,
            14,
            22,
            19,
            29,
            18,
            22,
            25,
            19,
            22,
            23,
            26,
            29,
            22,
            22,
            25,
            29,
            18,
            22,
            25,
            23,
            29,
            22,
            25,
            19,
            29,
            22,
            23,
            25,
            29,
            22,
            18,
            25,
            29,
            22,
            23,
            25,
            29,
            23,
            22,
            25
        ],
        "Y": [
            12,
            6,
            11,
            3,
            12,
            12,
            12,
            15,
            11,
            11,
            12,
            15,
            12,
            11,
            12,
            15,
            12,
            12,
            12,
            15,
            11,
            12,
            12,
            16,
            4,
            13,
            12,
            11,
            15,
            12,
            12,
            11,
            16,
            12,
            11,
            12,
            15,
            12,
            11,
            12,
            15
        ],
        "elm_info_gained": [
            0.29523586316781897,
            0.7589393508936928,
            0.08307543350694027,
            0.07512485511905646,
            0.07534541621798954,
            0.29537739212390257,
            0.08218419168758877,
            0.10897857343145972,
            0.12153495326922452,
            0.3512299638476515,
            0.38086454017114335,
            0.1676929392277144,
            0.1019155581901046,
            0.21924697528787393,
            0.11010509318310847,
            0.16981893922448263,
            0.07188209170969592,
            2.2635981612085723,
            0.1453168959848561,
            0.2236510934361644,
            0.2556302719578107,
            0.41810006529376303,
            0.14562731789365543,
            0.06330969613120824,
            0.08051781840055108,
            0.184835825705785,
            0.2268855567588121,
            0.10853435620041056,
            0.12762057894858136,
            0.11167844335995816,
            0.06872499291946138,
            0.11684949125144671,
            0.10072498924651438,
            0.30103066012239615,
            0.15766185747208042,
            0.15414879753363128,
            0.3833140552538326,
            0.19314361888362586,
            0.12710286332826615,
            0.1388232327901819
        ],
        "searched_object_indexes": [
            0,
            0,
            0,
            0,
            0,
            0,
            0,
            0,
            0,
            0,
            0,
            0,
            0,
            0,
            0,
            0,
            0,
            0,
            0,
            0,
            0,
            0,
            0,
            0,
            0,
            0,
            0,
            0,
            0,
            0,
            0,
            0,
            0,
            0,
            0,
            0,
            0,
            0,
            0,
            0
        ],
        "memory_set": [
            "person18565.png"
        ],
        "target_object": "TBD",
        "max_fixations": 41
    },
    "cmp_building_015_person_008.jpg": {
        "subject": "nnIBS Model",
        "dataset": "HSUBANOTT",
        "image_height": 24,
        "image_width": 32,
        "receptive_height": 1,
        "receptive_width": 1,
        "target_found": true,
        "target_bbox": [
            11,
            4,
            13,
            5
        ],
        "X": [
            16,
            14,
            19,
            12,
            17,
            23,
            8,
            5
        ],
        "Y": [
            12,
            14,
            11,
            8,
            5,
            5,
            10,
            12
        ],
        "elm_info_gained": [
            0.5241316969726696,
            0.4727625841967108,
            0.09136324990931996,
            0.08973512379967802,
            0.08061418491105554,
            0.076579483223506,
            0.21676345162769922,
            1.7482156452259472
        ],
        "searched_object_indexes": [
            0,
            0,
            0,
            0,
            0,
            0,
            0
        ],
        "memory_set": [
            "person177.png"
        ],
        "target_object": "TBD",
        "max_fixations": 41
    },
    "cmp_building_022_cat_009.jpg": {
        "subject": "nnIBS Model",
        "dataset": "HSUBANOTT",
        "image_height": 24,
        "image_width": 32,
        "receptive_height": 1,
        "receptive_width": 1,
        "target_found": true,
        "target_bbox": [
            7,
            23,
            8,
            25
        ],
        "X": [
            16,
            22,
            19,
            24,
            24
        ],
        "Y": [
            12,
            14,
            7,
            9,
            8
        ],
        "elm_info_gained": [
            0.9416038187377493,
            0.3773676865495341,
            0.4478512778093306,
            1.621795887935713,
            4.368908698739123
        ],
        "searched_object_indexes": [
            0,
            0,
            0,
            0
        ],
        "memory_set": [
            "cat1633.png"
        ],
        "target_object": "TBD",
        "max_fixations": 41
    },
    "cmp_building_033_cat_012.jpg": {
        "subject": "nnIBS Model",
        "dataset": "HSUBANOTT",
        "image_height": 24,
        "image_width": 32,
        "receptive_height": 1,
        "receptive_width": 1,
        "target_found": true,
        "target_bbox": [
            15,
            25,
            17,
            27
        ],
        "X": [
            16,
            20,
            25
        ],
        "Y": [
            12,
            12,
            16
        ],
        "elm_info_gained": [
            0.5134068055157183,
            0.41085706116570986,
            3.0281671325178796
        ],
        "searched_object_indexes": [
            0,
            0
        ],
        "memory_set": [
            "cat1919.png"
        ],
        "target_object": "TBD",
        "max_fixations": 41
    },
    "cmp_building_039_dog_007.jpg": {
        "subject": "nnIBS Model",
        "dataset": "HSUBANOTT",
        "image_height": 24,
        "image_width": 32,
        "receptive_height": 1,
        "receptive_width": 1,
        "target_found": true,
        "target_bbox": [
            0,
            26,
            2,
            27
        ],
        "X": [
            16,
            6,
            15,
            22,
            26,
            26
        ],
        "Y": [
            12,
            9,
            6,
            11,
            3,
            2
        ],
        "elm_info_gained": [
            0.3095770129372862,
            0.23619872280115642,
            0.07220158768098489,
            0.06478634166922835,
            1.0163512812193762,
            3.7433769863525925
        ],
        "searched_object_indexes": [
            0,
            0,
            0,
            0,
            0
        ],
        "memory_set": [
            "dog519.png"
        ],
        "target_object": "TBD",
        "max_fixations": 41
    },
    "cmp_building_046_sheep_001.jpg": {
        "subject": "nnIBS Model",
        "dataset": "HSUBANOTT",
        "image_height": 24,
        "image_width": 32,
        "receptive_height": 1,
        "receptive_width": 1,
        "target_found": true,
        "target_bbox": [
            13,
            7,
            15,
            8
        ],
        "X": [
            16,
            17,
            8
        ],
        "Y": [
            12,
            6,
            14
        ],
        "elm_info_gained": [
            0.41107993611305005,
            0.3057707754297169,
            0.44880515034460855
        ],
        "searched_object_indexes": [
            0,
            0
        ],
        "memory_set": [
            "sheep1548.png"
        ],
        "target_object": "TBD",
        "max_fixations": 41
    },
    "cmp_building_054_bird_010.jpg": {
        "subject": "nnIBS Model",
        "dataset": "HSUBANOTT",
        "image_height": 24,
        "image_width": 32,
        "receptive_height": 1,
        "receptive_width": 1,
        "target_found": true,
        "target_bbox": [
            22,
            25,
            23,
            27
        ],
        "X": [
            16,
            19,
            13,
            11,
            21,
            28,
            25,
            25
        ],
        "Y": [
            12,
            10,
            9,
            18,
            18,
            15,
            21,
            22
        ],
        "elm_info_gained": [
            0.24265474942861365,
            0.23196052407761705,
            0.06537117766494904,
            0.06420260129994074,
            0.07098900071185986,
            0.0714187841714865,
            2.5645939696822606,
            3.8214959495496887
        ],
        "searched_object_indexes": [
            0,
            0,
            0,
            0,
            0,
            0,
            0
        ],
        "memory_set": [
            "bird1519.png"
        ],
        "target_object": "TBD",
        "max_fixations": 41
    },
    "cmp_building_060_dog_017.jpg": {
        "subject": "nnIBS Model",
        "dataset": "HSUBANOTT",
        "image_height": 24,
        "image_width": 32,
        "receptive_height": 1,
        "receptive_width": 1,
        "target_found": true,
        "target_bbox": [
            18,
            26,
            19,
            28
        ],
        "X": [
            16,
            20,
            19,
            26
        ],
        "Y": [
            12,
            6,
            12,
            18
        ],
        "elm_info_gained": [
            0.24571995456585416,
            0.1976314699233601,
            0.06830155790099916,
            0.9738890611439405
        ],
        "searched_object_indexes": [
            0,
            0,
            0
        ],
        "memory_set": [
            "dog1200.png"
        ],
        "target_object": "TBD",
        "max_fixations": 41
    },
    "cmp_cakestand_003_food_002.jpg": {
        "subject": "nnIBS Model",
        "dataset": "HSUBANOTT",
        "image_height": 24,
        "image_width": 32,
        "receptive_height": 1,
        "receptive_width": 1,
        "target_found": true,
        "target_bbox": [
            18,
            9,
            19,
            11
        ],
        "X": [
            16,
            12,
            10
        ],
        "Y": [
            12,
            13,
            18
        ],
        "elm_info_gained": [
            0.9028999951576276,
            0.4511370718290731,
            3.381692589341457
        ],
        "searched_object_indexes": [
            0,
            0
        ],
        "memory_set": [
            "sandwich701.png"
        ],
        "target_object": "TBD",
        "max_fixations": 41
    },
    "cmp_field_007_farmanimals_007.jpg": {
        "subject": "nnIBS Model",
        "dataset": "HSUBANOTT",
        "image_height": 24,
        "image_width": 32,
        "receptive_height": 1,
        "receptive_width": 1,
        "target_found": true,
        "target_bbox": [
            19,
            16,
            21,
            18
        ],
        "X": [
            16,
            18,
            26,
            18
        ],
        "Y": [
            12,
            11,
            10,
            19
        ],
        "elm_info_gained": [
            1.3997165359685586,
            0.5877197002619158,
            0.08340478689286439,
            2.4906297052382715
        ],
        "searched_object_indexes": [
            0,
            0,
            0
        ],
        "memory_set": [
            "horse594.png"
        ],
        "target_object": "TBD",
        "max_fixations": 41
    },
    "cmp_jungle_007_bird_007.jpg": {
        "subject": "nnIBS Model",
        "dataset": "HSUBANOTT",
        "image_height": 24,
        "image_width": 32,
        "receptive_height": 1,
        "receptive_width": 1,
        "target_found": false,
        "target_bbox": [
            5,
            22,
            7,
            25
        ],
        "X": [
            16,
            13,
            15,
            16,
            5,
            12,
            15,
            15,
            12,
            12,
            15,
            16,
            15,
            12,
            13,
            15,
            17,
            16,
            12,
            15,
            15,
            5,
            12,
            15,
            15,
            15,
            12,
            12,
            15,
            15,
            12,
            14,
            15,
            5,
            12,
            16,
            15,
            16,
            13,
            15,
            15
        ],
        "Y": [
            12,
            10,
            10,
            15,
            8,
            11,
            10,
            16,
            11,
            11,
            10,
            15,
            10,
            11,
            10,
            15,
            10,
            15,
            11,
            15,
            10,
            9,
            11,
            15,
            10,
            10,
            11,
            10,
            15,
            10,
            11,
            10,
            15,
            9,
            11,
            10,
            15,
            16,
            11,
            10,
            15
        ],
        "elm_info_gained": [
            0.3326213321517717,
            0.6115612648427483,
            0.3150959927680493,
            0.0726414283167553,
            0.09613835031347194,
            0.21368706794439807,
            0.06855789784390547,
            0.08846116091099283,
            0.12500891874626008,
            0.1878025123059554,
            0.1333877896557942,
            0.15080309854835539,
            1.2820827669234955,
            0.07287148345260525,
            0.13537023416150623,
            0.07332524171263788,
            0.11927921020682544,
            0.35338050863883064,
            0.17722397063134435,
            0.4144667769792052,
            0.0712025221313367,
            0.3619101451931405,
            0.12192322509676587,
            0.18120810136493887,
            0.07780715128427182,
            0.3422321758375469,
            0.9693038229119407,
            0.28887819446106083,
            0.1848576152438909,
            0.6373629594142831,
            0.08137740854614067,
            0.3343313414454414,
            0.0705359599731529,
            0.08608949010727736,
            0.06823612310384874,
            0.40169442561118834,
            0.08130720651177892,
            0.1086706021670859,
            0.21013674285233486,
            0.4331959109387549
        ],
        "searched_object_indexes": [
            0,
            0,
            0,
            0,
            0,
            0,
            0,
            0,
            0,
            0,
            0,
            0,
            0,
            0,
            0,
            0,
            0,
            0,
            0,
            0,
            0,
            0,
            0,
            0,
            0,
            0,
            0,
            0,
            0,
            0,
            0,
            0,
            0,
            0,
            0,
            0,
            0,
            0,
            0,
            0
        ],
        "memory_set": [
            "bird332.png"
        ],
        "target_object": "TBD",
        "max_fixations": 41
    },
    "cmp_mountain_004_sheep_001.jpg": {
        "subject": "nnIBS Model",
        "dataset": "HSUBANOTT",
        "image_height": 24,
        "image_width": 32,
        "receptive_height": 1,
        "receptive_width": 1,
        "target_found": false,
        "target_bbox": [
            7,
            2,
            9,
            4
        ],
        "X": [
            16,
            15,
            15,
            22,
            9,
            16,
            16,
            22,
            25,
            16,
            16,
            22,
            25,
            16,
            22,
            16,
            22,
            16,
            22,
            16,
            23,
            25,
            21,
            23,
            15,
            16,
            10,
            22,
            16,
            16,
            10,
            22,
            16,
            16,
            11,
            22,
            15,
            16,
            10,
            22,
            16
        ],
        "Y": [
            12,
            16,
            10,
            11,
            13,
            16,
            10,
            11,
            15,
            16,
            10,
            11,
            16,
            16,
            18,
            10,
            11,
            16,
            10,
            10,
            11,
            15,
            10,
            10,
            10,
            16,
            12,
            11,
            10,
            16,
            12,
            10,
            10,
            16,
            5,
            10,
            10,
            16,
            13,
            11,
            10
        ],
        "elm_info_gained": [
            1.2187843367707394,
            0.37959625107175204,
            0.25198802581173,
            0.07918643283901415,
            0.08745689609574192,
            0.09457132585586159,
            0.09144600406815462,
            0.07199586394074967,
            0.10534683395831661,
            0.10086951751969862,
            0.2584413907349659,
            0.07376437438653664,
            0.08449181604823218,
            0.10391036495651003,
            0.0890784822909693,
            0.16421998246135847,
            0.2013039362463258,
            0.08565803794099107,
            0.09019343984544048,
            0.08208980884508417,
            0.08749585066614908,
            0.0951183935715013,
            0.11127369834054579,
            0.08376052670364695,
            0.08523406265348232,
            0.10437610046556728,
            0.08046609742617906,
            0.10940352115078761,
            0.10237787593308083,
            0.0797008443186411,
            0.0962930463868968,
            0.1286730874043374,
            0.08354869820055286,
            0.07517057478568595,
            0.11885759912764446,
            0.10906562757283374,
            0.07745150393815176,
            0.09071254645081685,
            0.08584285653186076,
            0.07685451903066845
        ],
        "searched_object_indexes": [
            0,
            0,
            0,
            0,
            0,
            0,
            0,
            0,
            0,
            0,
            0,
            0,
            0,
            0,
            0,
            0,
            0,
            0,
            0,
            0,
            0,
            0,
            0,
            0,
            0,
            0,
            0,
            0,
            0,
            0,
            0,
            0,
            0,
            0,
            0,
            0,
            0,
            0,
            0,
            0
        ],
        "memory_set": [
            "sheep796.png"
        ],
        "target_object": "TBD",
        "max_fixations": 41
    },
    "cmp_mountain_019_sheep_007.jpg": {
        "subject": "nnIBS Model",
        "dataset": "HSUBANOTT",
        "image_height": 24,
        "image_width": 32,
        "receptive_height": 1,
        "receptive_width": 1,
        "target_found": true,
        "target_bbox": [
            17,
            4,
            19,
            6
        ],
        "X": [
            16,
            15,
            14,
            10,
            5,
            17,
            7,
            9,
            6
        ],
        "Y": [
            12,
            8,
            13,
            2,
            5,
            8,
            11,
            2,
            18
        ],
        "elm_info_gained": [
            0.24370188530169484,
            0.26786281830746034,
            0.06942018561657652,
            0.09814622367592,
            0.06855992268968748,
            0.06233134425265832,
            0.14259999984634328,
            0.07279353940489272,
            0.705684555509947
        ],
        "searched_object_indexes": [
            0,
            0,
            0,
            0,
            0,
            0,
            0,
            0
        ],
        "memory_set": [
            "sheep119.png"
        ],
        "target_object": "TBD",
        "max_fixations": 41
    },
    "cmp_office_001_pottedplant_001.jpg": {
        "subject": "nnIBS Model",
        "dataset": "HSUBANOTT",
        "image_height": 24,
        "image_width": 32,
        "receptive_height": 1,
        "receptive_width": 1,
        "target_found": true,
        "target_bbox": [
            20,
            29,
            22,
            31
        ],
        "X": [
            16,
            14,
            10,
            12,
            5,
            16,
            22,
            13,
            18,
            26,
            30,
            30
        ],
        "Y": [
            12,
            8,
            10,
            5,
            8,
            13,
            12,
            5,
            9,
            16,
            19,
            20
        ],
        "elm_info_gained": [
            0.7479283547099148,
            0.33932592987910026,
            0.08634947005872383,
            0.09136048980564934,
            0.06960298644927698,
            0.06593916250673645,
            0.07373075305685883,
            0.0708101000278666,
            0.0669229722613684,
            0.14893156987073738,
            1.7010702361009273,
            3.6401606347498223
        ],
        "searched_object_indexes": [
            0,
            0,
            0,
            0,
            0,
            0,
            0,
            0,
            0,
            0,
            0
        ],
        "memory_set": [
            "potted plant870.png"
        ],
        "target_object": "TBD",
        "max_fixations": 41
    },
    "cmp_seabottom_001_bottle_001.jpg": {
        "subject": "nnIBS Model",
        "dataset": "HSUBANOTT",
        "image_height": 24,
        "image_width": 32,
        "receptive_height": 1,
        "receptive_width": 1,
        "target_found": true,
        "target_bbox": [
            9,
            12,
            11,
            13
        ],
        "X": [
            16,
            19,
            13
        ],
        "Y": [
            12,
            12,
            10
        ],
        "elm_info_gained": [
            0.33634167176969365,
            0.4532993417134753,
            2.302194629602365
        ],
        "searched_object_indexes": [
            0,
            0
        ],
        "memory_set": [
            "bottle1337.png"
        ],
        "target_object": "TBD",
        "max_fixations": 41
    },
    "cmp_shelves_016_cup_001.jpg": {
        "subject": "nnIBS Model",
        "dataset": "HSUBANOTT",
        "image_height": 24,
        "image_width": 32,
        "receptive_height": 1,
        "receptive_width": 1,
        "target_found": true,
        "target_bbox": [
            4,
            22,
            5,
            23
        ],
        "X": [
            16,
            10,
            21,
            23
        ],
        "Y": [
            12,
            10,
            8,
            5
        ],
        "elm_info_gained": [
            0.4166917820774369,
            0.4421877884476902,
            0.16435749292167912,
            3.2570822512591757
        ],
        "searched_object_indexes": [
            0,
            0,
            0
        ],
        "memory_set": [
            "cup436.png"
        ],
        "target_object": "TBD",
        "max_fixations": 41
    },
    "cmp_shelves_018_remote_002.jpg": {
        "subject": "nnIBS Model",
        "dataset": "HSUBANOTT",
        "image_height": 24,
        "image_width": 32,
        "receptive_height": 1,
        "receptive_width": 1,
        "target_found": true,
        "target_bbox": [
            7,
            27,
            9,
            28
        ],
        "X": [
            16,
            8,
            13,
            23,
            26,
            27
        ],
        "Y": [
            12,
            12,
            13,
            13,
            9,
            8
        ],
        "elm_info_gained": [
            0.31514433532233765,
            0.22027319307008372,
            0.06937453729349292,
            0.0747039384995374,
            1.704447604624592,
            4.123503786206426
        ],
        "searched_object_indexes": [
            0,
            0,
            0,
            0,
            0
        ],
        "memory_set": [
            "remote24.png"
        ],
        "target_object": "TBD",
        "max_fixations": 41
    },
    "cmp_shelves_030_book_003.jpg": {
        "subject": "nnIBS Model",
        "dataset": "HSUBANOTT",
        "image_height": 24,
        "image_width": 32,
        "receptive_height": 1,
        "receptive_width": 1,
        "target_found": false,
        "target_bbox": [
            0,
            19,
            0,
            21
        ],
        "X": [
            16,
            12,
            21,
            22,
            8,
            3,
            9,
            10,
            4,
            14,
            9,
            9,
            3,
            4,
            9,
            9,
            3,
            3,
            13,
            9,
            9,
            3,
            4,
            10,
            9,
            3,
            3,
            3,
            9,
            4,
            4,
            9,
            12,
            3,
            9,
            9,
            10,
            3,
            9,
            3,
            13
        ],
        "Y": [
            12,
            7,
            19,
            11,
            9,
            5,
            15,
            16,
            11,
            12,
            16,
            9,
            10,
            4,
            15,
            8,
            9,
            4,
            12,
            8,
            16,
            5,
            11,
            8,
            16,
            5,
            9,
            13,
            16,
            5,
            9,
            8,
            12,
            4,
            16,
            9,
            19,
            5,
            16,
            3,
            12
        ],
        "elm_info_gained": [
            0.48403024656043014,
            0.5104229956847135,
            0.12871525826011065,
            0.07118887247039962,
            0.072362927520642,
            0.06726213029891323,
            0.07782850287663706,
            0.07093695509358215,
            0.07109329807261447,
            0.13581374582649264,
            0.06665817113810638,
            0.08176259737681596,
            0.0824984633632475,
            0.07681279966585011,
            0.06943696437258857,
            0.06545446010370182,
            0.11963410805141364,
            0.06619458429833978,
            0.07202974631503455,
            0.0818053206367769,
            0.08435686590751088,
            0.07048731358705046,
            0.07180967680927704,
            0.0664998303395611,
            0.09072289574419591,
            0.0746512767360326,
            0.07248385209332313,
            0.07735190810182002,
            0.08850060297304849,
            0.0702397387080422,
            0.07635051044831102,
            0.06716906890734718,
            0.07370465636747174,
            0.07618867579385752,
            0.07273984411953921,
            0.06904297627963203,
            0.07654016957639108,
            0.1340768818224501,
            0.08031496978488607,
            0.07788951875538604
        ],
        "searched_object_indexes": [
            0,
            0,
            0,
            0,
            0,
            0,
            0,
            0,
            0,
            0,
            0,
            0,
            0,
            0,
            0,
            0,
            0,
            0,
            0,
            0,
            0,
            0,
            0,
            0,
            0,
            0,
            0,
            0,
            0,
            0,
            0,
            0,
            0,
            0,
            0,
            0,
            0,
            0,
            0,
            0
        ],
        "memory_set": [
            "book171.png"
        ],
        "target_object": "TBD",
        "max_fixations": 41
    },
    "cmp_shelves_035_book_008.jpg": {
        "subject": "nnIBS Model",
        "dataset": "HSUBANOTT",
        "image_height": 24,
        "image_width": 32,
        "receptive_height": 1,
        "receptive_width": 1,
        "target_found": true,
        "target_bbox": [
            17,
            4,
            17,
            6
        ],
        "X": [
            16,
            22,
            25,
            19,
            19,
            11,
            8,
            6
        ],
        "Y": [
            12,
            4,
            8,
            8,
            14,
            17,
            21,
            17
        ],
        "elm_info_gained": [
            0.3629463251583518,
            0.267610285156403,
            0.07500760745509719,
            0.06311378332675012,
            0.0639366004958192,
            0.08428032973212163,
            0.08258552105978109,
            0.3187361633306392
        ],
        "searched_object_indexes": [
            0,
            0,
            0,
            0,
            0,
            0,
            0
        ],
        "memory_set": [
            "book271.png"
        ],
        "target_object": "TBD",
        "max_fixations": 41
    },
    "cmp_shelves_040_book_013.jpg": {
        "subject": "nnIBS Model",
        "dataset": "HSUBANOTT",
        "image_height": 24,
        "image_width": 32,
        "receptive_height": 1,
        "receptive_width": 1,
        "target_found": true,
        "target_bbox": [
            9,
            3,
            10,
            5
        ],
        "X": [
            16,
            17,
            20,
            24,
            11,
            19,
            5
        ],
        "Y": [
            12,
            9,
            13,
            9,
            5,
            5,
            9
        ],
        "elm_info_gained": [
            0.6690969041804129,
            0.4275392114078188,
            0.06942661672922265,
            0.06503836506255317,
            0.0643923038110797,
            0.06673671390762219,
            0.35863216799146835
        ],
        "searched_object_indexes": [
            0,
            0,
            0,
            0,
            0,
            0
        ],
        "memory_set": [
            "book879.png"
        ],
        "target_object": "TBD",
        "max_fixations": 41
    },
    "cmp_shelves_046_toys_005.jpg": {
        "subject": "nnIBS Model",
        "dataset": "HSUBANOTT",
        "image_height": 24,
        "image_width": 32,
        "receptive_height": 1,
        "receptive_width": 1,
        "target_found": true,
        "target_bbox": [
            3,
            9,
            4,
            10
        ],
        "X": [
            16,
            18,
            9,
            22,
            10
        ],
        "Y": [
            12,
            8,
            11,
            11,
            4
        ],
        "elm_info_gained": [
            0.3807353294936367,
            0.4005126908048163,
            0.07695924705771716,
            0.07101700725009819,
            1.8863695874324935
        ],
        "searched_object_indexes": [
            0,
            0,
            0,
            0
        ],
        "memory_set": [
            "motorcycle551.png"
        ],
        "target_object": "TBD",
        "max_fixations": 41
    },
    "cmp_shelves_054_toys_013.jpg": {
        "subject": "nnIBS Model",
        "dataset": "HSUBANOTT",
        "image_height": 24,
        "image_width": 32,
        "receptive_height": 1,
        "receptive_width": 1,
        "target_found": true,
        "target_bbox": [
            7,
            25,
            8,
            26
        ],
        "X": [
            16,
            12,
            19,
            25
        ],
        "Y": [
            12,
            13,
            10,
            8
        ],
        "elm_info_gained": [
            0.6840388669208368,
            0.7667030334635841,
            0.0989879631579389,
            1.4128488326262205
        ],
        "searched_object_indexes": [
            0,
            0,
            0
        ],
        "memory_set": [
            "truck319.png"
        ],
        "target_object": "TBD",
        "max_fixations": 41
    },
    "cmp_shelves_059_toys_018.jpg": {
        "subject": "nnIBS Model",
        "dataset": "HSUBANOTT",
        "image_height": 24,
        "image_width": 32,
        "receptive_height": 1,
        "receptive_width": 1,
        "target_found": true,
        "target_bbox": [
            1,
            14,
            3,
            16
        ],
        "X": [
            16,
            12,
            19,
            16
        ],
        "Y": [
            12,
            9,
            12,
            3
        ],
        "elm_info_gained": [
            0.48782432698984557,
            0.5151838451453058,
            0.0771872098717469,
            0.47224380018765294
        ],
        "searched_object_indexes": [
            0,
            0,
            0
        ],
        "memory_set": [
            "truck196.png"
        ],
        "target_object": "TBD",
        "max_fixations": 41
    },
    "cmp_shelves_075_toys_034.jpg": {
        "subject": "nnIBS Model",
        "dataset": "HSUBANOTT",
        "image_height": 24,
        "image_width": 32,
        "receptive_height": 1,
        "receptive_width": 1,
        "target_found": true,
        "target_bbox": [
            6,
            19,
            7,
            21
        ],
        "X": [
            16,
            21,
            10,
            17,
            11,
            22,
            22,
            16,
            19
        ],
        "Y": [
            12,
            11,
            12,
            17,
            21,
            17,
            12,
            17,
            6
        ],
        "elm_info_gained": [
            0.32448744158903275,
            0.39276557661137884,
            0.09902809147826083,
            0.0658634163843262,
            0.06931923789619894,
            0.0733007466751657,
            0.11678586351687412,
            0.0655085479206234,
            0.7446443093865777
        ],
        "searched_object_indexes": [
            0,
            0,
            0,
            0,
            0,
            0,
            0,
            0
        ],
        "memory_set": [
            "airplane1062.png"
        ],
        "target_object": "TBD",
        "max_fixations": 41
    },
    "cmp_shelves_081_knife_004.jpg": {
        "subject": "nnIBS Model",
        "dataset": "HSUBANOTT",
        "image_height": 24,
        "image_width": 32,
        "receptive_height": 1,
        "receptive_width": 1,
        "target_found": false,
        "target_bbox": [
            7,
            22,
            7,
            24
        ],
        "X": [
            16,
            15,
            9,
            16,
            11,
            8,
            16,
            9,
            9,
            9,
            11,
            16,
            16,
            9,
            12,
            15,
            16,
            9,
            10,
            15,
            16,
            10,
            11,
            8,
            16,
            16,
            10,
            12,
            15,
            15,
            9,
            11,
            15,
            15,
            9,
            10,
            15,
            16,
            12,
            10,
            15
        ],
        "Y": [
            12,
            8,
            9,
            15,
            20,
            17,
            22,
            19,
            19,
            16,
            21,
            15,
            22,
            18,
            21,
            16,
            22,
            17,
            20,
            15,
            22,
            22,
            20,
            17,
            16,
            22,
            20,
            20,
            16,
            23,
            19,
            21,
            16,
            22,
            17,
            19,
            15,
            22,
            21,
            18,
            22
        ],
        "elm_info_gained": [
            0.2634954173864984,
            0.27114218809563695,
            0.073333589992047,
            0.07158521819040874,
            0.08612025381582587,
            0.10187293986424747,
            0.26096412954953074,
            0.08467641616626101,
            0.1519051823065627,
            0.08290081083658005,
            0.07557636277216452,
            0.09092224071409895,
            0.10299148400013204,
            0.21020717889824722,
            0.079645027007558,
            0.16321861310150024,
            0.07841495907387663,
            0.14676928633768083,
            0.10926282349667732,
            0.0752741509851293,
            0.08709726620723289,
            0.09317980552466128,
            0.07885458303393525,
            0.0856083295240972,
            0.08853774989842121,
            0.07907014557016982,
            0.08372815249193148,
            0.19151200933304463,
            0.7036277415149432,
            0.08178806735344098,
            0.0899916607081568,
            0.08986223668781126,
            0.13214229468108973,
            0.09180400551389609,
            0.13856550263168502,
            0.13503207271334566,
            0.07589124119646105,
            0.08385897375858618,
            0.09638120082720161,
            0.09382497394846627
        ],
        "searched_object_indexes": [
            0,
            0,
            0,
            0,
            0,
            0,
            0,
            0,
            0,
            0,
            0,
            0,
            0,
            0,
            0,
            0,
            0,
            0,
            0,
            0,
            0,
            0,
            0,
            0,
            0,
            0,
            0,
            0,
            0,
            0,
            0,
            0,
            0,
            0,
            0,
            0,
            0,
            0,
            0,
            0
        ],
        "memory_set": [
            "knife77.png"
        ],
        "target_object": "TBD",
        "max_fixations": 41
    },
    "cmp_shelves_089_vase_008.jpg": {
        "subject": "nnIBS Model",
        "dataset": "HSUBANOTT",
        "image_height": 24,
        "image_width": 32,
        "receptive_height": 1,
        "receptive_width": 1,
        "target_found": true,
        "target_bbox": [
            21,
            12,
            23,
            13
        ],
        "X": [
            16,
            9,
            20,
            22,
            13
        ],
        "Y": [
            12,
            14,
            15,
            15,
            21
        ],
        "elm_info_gained": [
            0.29015086654777456,
            0.36342331988119825,
            0.1838525802908445,
            0.06413860049872455,
            0.8720738451292734
        ],
        "searched_object_indexes": [
            0,
            0,
            0,
            0
        ],
        "memory_set": [
            "vase1198.png"
        ],
        "target_object": "TBD",
        "max_fixations": 41
    },
    "cmp_shelves_096_teddybear_009.jpg": {
        "subject": "nnIBS Model",
        "dataset": "HSUBANOTT",
        "image_height": 24,
        "image_width": 32,
        "receptive_height": 1,
        "receptive_width": 1,
        "target_found": true,
        "target_bbox": [
            7,
            5,
            9,
            7
        ],
        "X": [
            16,
            7,
            17,
            7
        ],
        "Y": [
            12,
            16,
            16,
            8
        ],
        "elm_info_gained": [
            0.309069429712664,
            0.33546947790028436,
            0.06768317212134015,
            0.2067826139786955
        ],
        "searched_object_indexes": [
            0,
            0,
            0
        ],
        "memory_set": [
            "teddy bear34.png"
        ],
        "target_object": "TBD",
        "max_fixations": 41
    },
    "cmp_shelves_103_teddybear_016.jpg": {
        "subject": "nnIBS Model",
        "dataset": "HSUBANOTT",
        "image_height": 24,
        "image_width": 32,
        "receptive_height": 1,
        "receptive_width": 1,
        "target_found": true,
        "target_bbox": [
            9,
            10,
            11,
            12
        ],
        "X": [
            16,
            7,
            12
        ],
        "Y": [
            12,
            10,
            10
        ],
        "elm_info_gained": [
            0.3063870714553439,
            0.7251010824938127,
            4.102952262094395
        ],
        "searched_object_indexes": [
            0,
            0
        ],
        "memory_set": [
            "teddy bear1654.png"
        ],
        "target_object": "TBD",
        "max_fixations": 41
    },
    "cmp_shelves_108_teddybear_021.jpg": {
        "subject": "nnIBS Model",
        "dataset": "HSUBANOTT",
        "image_height": 24,
        "image_width": 32,
        "receptive_height": 1,
        "receptive_width": 1,
        "target_found": true,
        "target_bbox": [
            18,
            10,
            20,
            11
        ],
        "X": [
            16,
            9,
            11,
            11
        ],
        "Y": [
            12,
            10,
            13,
            18
        ],
        "elm_info_gained": [
            0.5546676690313145,
            0.3706542006743953,
            0.12822222505923078,
            0.7862307729498978
        ],
        "searched_object_indexes": [
            0,
            0,
            0
        ],
        "memory_set": [
            "teddy bear1557.png"
        ],
        "target_object": "TBD",
        "max_fixations": 41
    },
    "cmp_shelves_109_teddybear_022.jpg": {
        "subject": "nnIBS Model",
        "dataset": "HSUBANOTT",
        "image_height": 24,
        "image_width": 32,
        "receptive_height": 1,
        "receptive_width": 1,
        "target_found": true,
        "target_bbox": [
            4,
            24,
            6,
            26
        ],
        "X": [
            16,
            12,
            22,
            25
        ],
        "Y": [
            12,
            11,
            11,
            5
        ],
        "elm_info_gained": [
            0.5932978604473664,
            0.6076891115416075,
            0.07524322846140234,
            0.529759013973527
        ],
        "searched_object_indexes": [
            0,
            0,
            0
        ],
        "memory_set": [
            "teddy bear838.png"
        ],
        "target_object": "TBD",
        "max_fixations": 41
    },
    "cmp_shelves_111_pottedplant_002.jpg": {
        "subject": "nnIBS Model",
        "dataset": "HSUBANOTT",
        "image_height": 24,
        "image_width": 32,
        "receptive_height": 1,
        "receptive_width": 1,
        "target_found": false,
        "target_bbox": [
            19,
            3,
            21,
            5
        ],
        "X": [
            16,
            20,
            19,
            22,
            15,
            19,
            19,
            22,
            25,
            18,
            19,
            22,
            24,
            18,
            19,
            22,
            15,
            25,
            19,
            22,
            26,
            25,
            19,
            15,
            9,
            22,
            19,
            22,
            19,
            25,
            25,
            22,
            19,
            29,
            19,
            25,
            25,
            22,
            19,
            25,
            25
        ],
        "Y": [
            12,
            12,
            12,
            12,
            12,
            17,
            12,
            12,
            15,
            18,
            12,
            12,
            16,
            17,
            12,
            12,
            19,
            15,
            12,
            12,
            20,
            15,
            12,
            12,
            12,
            13,
            12,
            12,
            13,
            16,
            19,
            12,
            12,
            19,
            18,
            19,
            16,
            12,
            12,
            20,
            15
        ],
        "elm_info_gained": [
            0.5402913633146784,
            0.5547996989898824,
            0.24056844195754995,
            0.07320214270835317,
            0.06928226795243568,
            0.21860727959623671,
            0.3222470477575885,
            0.10599212003014782,
            0.06785413361039346,
            0.10119160288088842,
            0.143065314395993,
            0.11904291088453976,
            0.06886453974627474,
            0.17826154004051709,
            0.42108719971558073,
            0.1411500427437908,
            0.09455085021777007,
            0.18829010950921804,
            0.0987342627388804,
            0.06957440943516761,
            0.08402954795079913,
            0.0910258773943207,
            0.0739202640424162,
            0.0881568927724836,
            0.1302671140735651,
            0.10608826748282218,
            0.07745809491887866,
            0.10989221130865943,
            0.0775297261773993,
            0.07894164534884869,
            0.10444875373692027,
            0.10035587109206102,
            0.08329022961956813,
            0.0713968152872225,
            0.11081953508635686,
            0.10852563560590195,
            0.11315792246692703,
            0.1345893849551658,
            0.07313055798417295,
            0.07221747683870965
        ],
        "searched_object_indexes": [
            0,
            0,
            0,
            0,
            0,
            0,
            0,
            0,
            0,
            0,
            0,
            0,
            0,
            0,
            0,
            0,
            0,
            0,
            0,
            0,
            0,
            0,
            0,
            0,
            0,
            0,
            0,
            0,
            0,
            0,
            0,
            0,
            0,
            0,
            0,
            0,
            0,
            0,
            0,
            0
        ],
        "memory_set": [
            "potted plant455.png"
        ],
        "target_object": "TBD",
        "max_fixations": 41
    },
    "cmp_sky_001_kite_001.jpg": {
        "subject": "nnIBS Model",
        "dataset": "HSUBANOTT",
        "image_height": 24,
        "image_width": 32,
        "receptive_height": 1,
        "receptive_width": 1,
        "target_found": false,
        "target_bbox": [
            1,
            4,
            2,
            6
        ],
        "X": [
            16,
            21,
            18,
            26,
            25,
            22,
            26,
            27,
            25,
            26,
            22,
            26,
            25,
            28,
            23,
            26,
            21,
            25,
            22,
            26,
            22,
            26,
            26,
            26,
            21,
            25,
            26,
            25,
            22,
            16,
            26,
            25,
            9,
            21,
            26,
            25,
            12,
            20,
            26,
            25,
            13
        ],
        "Y": [
            12,
            16,
            2,
            15,
            21,
            17,
            15,
            8,
            21,
            16,
            17,
            15,
            21,
            9,
            5,
            15,
            16,
            21,
            7,
            16,
            17,
            21,
            15,
            16,
            17,
            21,
            15,
            20,
            17,
            15,
            16,
            21,
            17,
            17,
            16,
            20,
            20,
            17,
            15,
            21,
            20
        ],
        "elm_info_gained": [
            0.3842443107895568,
            0.2655533879827983,
            0.10765795978534855,
            0.07388629973852391,
            0.09210969085023095,
            0.10886544787389314,
            0.06311226486282,
            0.200823242790345,
            0.0767039518539674,
            0.11095539678319358,
            0.9995454074555579,
            0.11154059226409312,
            0.06233039386167119,
            0.06800383847242483,
            0.06796450117849409,
            0.07959347599953767,
            0.09421465044875592,
            0.06278777709602476,
            0.10816417348999323,
            0.1024205431346972,
            0.15969997291387666,
            0.06773652739409093,
            0.0726726437772399,
            0.09484353528391579,
            0.1125756439865441,
            0.2906458776670603,
            0.07255937337088081,
            0.10408499514576126,
            0.0629973094593524,
            0.4249592401383378,
            0.2390261569134572,
            0.07247109564364741,
            0.07564966234346164,
            0.1360823505838223,
            0.10271751157862673,
            0.06375501571831842,
            0.07172833562770738,
            0.06746688635407874,
            0.07825233688965126,
            0.0625665481634992
        ],
        "searched_object_indexes": [
            0,
            0,
            0,
            0,
            0,
            0,
            0,
            0,
            0,
            0,
            0,
            0,
            0,
            0,
            0,
            0,
            0,
            0,
            0,
            0,
            0,
            0,
            0,
            0,
            0,
            0,
            0,
            0,
            0,
            0,
            0,
            0,
            0,
            0,
            0,
            0,
            0,
            0,
            0,
            0
        ],
        "memory_set": [
            "stm_sky_001_kite_001_016.png"
        ],
        "target_object": "TBD",
        "max_fixations": 41
    },
    "cmp_snow_001_person_001.jpg": {
        "subject": "nnIBS Model",
        "dataset": "HSUBANOTT",
        "image_height": 24,
        "image_width": 32,
        "receptive_height": 1,
        "receptive_width": 1,
        "target_found": true,
        "target_bbox": [
            9,
            2,
            11,
            4
        ],
        "X": [
            16,
            12,
            15,
            12,
            11,
            11,
            5,
            4
        ],
        "Y": [
            12,
            15,
            10,
            20,
            21,
            16,
            18,
            11
        ],
        "elm_info_gained": [
            0.521171181446741,
            0.7498571383272834,
            0.07282201985949968,
            0.15192877557861473,
            0.13326341307585873,
            0.1187190873440922,
            0.07804875096229623,
            2.1294368461975957
        ],
        "searched_object_indexes": [
            0,
            0,
            0,
            0,
            0,
            0,
            0
        ],
        "memory_set": [
            "person10154.png"
        ],
        "target_object": "TBD",
        "max_fixations": 41
    },
    "cmp_yard_005_animal_003.jpg": {
        "subject": "nnIBS Model",
        "dataset": "HSUBANOTT",
        "image_height": 24,
        "image_width": 32,
        "receptive_height": 1,
        "receptive_width": 1,
        "target_found": true,
        "target_bbox": [
            1,
            8,
            3,
            9
        ],
        "X": [
            16,
            11,
            16,
            9
        ],
        "Y": [
            12,
            9,
            5,
            3
        ],
        "elm_info_gained": [
            0.8999104134220159,
            0.46079373250232164,
            0.10785721150176993,
            2.190801816922014
        ],
        "searched_object_indexes": [
            0,
            0,
            0
        ],
        "memory_set": [
            "cat1855.png"
        ],
        "target_object": "TBD",
        "max_fixations": 41
    }
}